irene_pro/__init__.py
irene_pro/logics.py
irene_pro/widgets.py
irene_pro1-0.0.79.dist-info/LICENSE
irene_pro1-0.0.79.dist-info/METADATA
irene_pro1-0.0.79.dist-info/WHEEL
irene_pro1-0.0.79.dist-info/top_level.txt
irene_pro1-0.0.79.dist-info/RECORD
