Metadata-Version: 2.1
Name: irene-pro1
Version: 0.0.79
Summary: Use customized GUI
Author: Irene coldsober
Author-email: <irene.study.2023@gmail.com>
Keywords: tkinter,widget,gui
Classifier: Development Status :: 5 - Production/Stable
Classifier: Intended Audience :: Developers
Classifier: Programming Language :: Python :: 3
Classifier: Operating System :: Unix
Classifier: Operating System :: MacOS :: MacOS X
Classifier: Operating System :: Microsoft :: Windows
License-File: LICENSE
Requires-Dist: pywin32
Requires-Dist: opencv-python
Requires-Dist: pyperclip
Requires-Dist: tkcalendar
Requires-Dist: ttkthemes
Requires-Dist: numpy
